yadr/__init__.py
yadr/__main__.py
yadr/base.py
yadr/encode.py
yadr/lex.py
yadr/maps.py
yadr/model.py
yadr/operator.py
yadr/parser.py
yadr/pools.py
yadr/py.typed
yadr/yadr.py
yadr/data/__init__.py
yadr/data/dice_maps.yadn
yadr-0.1.4.dist-info/LICENSE
yadr-0.1.4.dist-info/METADATA
yadr-0.1.4.dist-info/WHEEL
yadr-0.1.4.dist-info/top_level.txt
yadr-0.1.4.dist-info/RECORD
