Metadata-Version: 2.1
Name: yadr
Version: 0.1.4
Summary: Yet another dice roller for Python.
Home-page: https://github.com/pji/yadr
Author: Paul J. Iutzi
Author-email: pji@mac.com
Project-URL: Bug Tracker, https://github.com/pji/yadr/issues
Classifier: Programming Language :: Python :: 3.10
Classifier: License :: OSI Approved :: MIT License
Classifier: Operating System :: OS Independent
Requires-Python: >=3.10
License-File: LICENSE
